{
"nodes":[
{"name":"KLARA","group":5,"group1":1, "weight":100},
{"name":"ELSE","group":5,"group1":1, "weight":100},
{"name":"JOSEF","group":5,"group1":2, "weight":100},
{"name":"DIE AUFSEHERIN","group":5,"group1":1, "weight":100},
{"name":"DER WACHTMEISTER","group":5,"group1":5, "weight":100},
{"name":"DER GEFÄNGNISDIREKTOR","group":5,"group1":8, "weight":100},
{"name":"EIN DIENSTMÄDCHEN","group":5,"group1":1, "weight":100},
{"name":"LINDEKUH","group":5,"group1":10, "weight":100},
{"name":"DR SCHWARZKOPF","group":5,"group1":15, "weight":100},
{"name":"FRAU OBERST","group":5,"group1":7, "weight":100}
],
"links":[
{"source":0,"target":1,"value":49},
{"source":0,"target":2,"value":121},
{"source":0,"target":1,"value":49},
{"source":0,"target":2,"value":121},
{"source":0,"target":3,"value":9},
{"source":0,"target":2,"value":121},
{"source":0,"target":4,"value":9},
{"source":0,"target":3,"value":9},
{"source":0,"target":2,"value":121},
{"source":0,"target":1,"value":49},
{"source":0,"target":4,"value":9},
{"source":0,"target":3,"value":9},
{"source":0,"target":2,"value":121},
{"source":0,"target":5,"value":1},
{"source":0,"target":4,"value":9},
{"source":0,"target":2,"value":121},
{"source":0,"target":1,"value":49},
{"source":0,"target":6,"value":1},
{"source":0,"target":7,"value":9},
{"source":0,"target":2,"value":121},
{"source":0,"target":7,"value":9},
{"source":0,"target":2,"value":121},
{"source":0,"target":1,"value":49},
{"source":0,"target":2,"value":121},
{"source":0,"target":1,"value":49},
{"source":0,"target":8,"value":4},
{"source":0,"target":1,"value":49},
{"source":0,"target":2,"value":121},
{"source":0,"target":9,"value":1},
{"source":0,"target":7,"value":9},
{"source":0,"target":8,"value":4},
{"source":0,"target":2,"value":121},
{"source":1,"target":2,"value":36},
{"source":1,"target":4,"value":4},
{"source":1,"target":3,"value":1},
{"source":1,"target":2,"value":36},
{"source":1,"target":5,"value":1},
{"source":1,"target":4,"value":4},
{"source":1,"target":2,"value":36},
{"source":1,"target":2,"value":36},
{"source":1,"target":2,"value":36},
{"source":1,"target":8,"value":1},
{"source":1,"target":2,"value":36},
{"source":2,"target":4,"value":9},
{"source":2,"target":3,"value":4},
{"source":2,"target":4,"value":9},
{"source":2,"target":3,"value":4},
{"source":2,"target":5,"value":1},
{"source":2,"target":4,"value":9},
{"source":2,"target":7,"value":4},
{"source":2,"target":8,"value":4},
{"source":2,"target":9,"value":1},
{"source":2,"target":7,"value":4},
{"source":2,"target":8,"value":4},
{"source":3,"target":4,"value":4},
{"source":3,"target":4,"value":4},
{"source":4,"target":5,"value":1},
{"source":7,"target":9,"value":1},
{"source":7,"target":8,"value":1},
{"source":8,"target":9,"value":1}
]
}