{
"nodes":[
{"name":"LA BELLA CENCI","group":5,"group1":1, "weight":100},
{"name":"URL","group":5,"group1":1, "weight":100},
{"name":"HOLLRIEDER","group":5,"group1":1, "weight":100},
{"name":"MUSMANN","group":5,"group1":1, "weight":100},
{"name":"LIPSIUS","group":5,"group1":2, "weight":100},
{"name":"DER PRÄSIDENT DER SEZESSION","group":5,"group1":3, "weight":100}
],
"links":[
{"source":0,"target":1,"value":1},
{"source":0,"target":2,"value":4},
{"source":0,"target":3,"value":4},
{"source":0,"target":5,"value":1},
{"source":0,"target":3,"value":4},
{"source":0,"target":4,"value":1},
{"source":0,"target":3,"value":4},
{"source":0,"target":2,"value":4},
{"source":1,"target":2,"value":16},
{"source":1,"target":3,"value":16},
{"source":1,"target":2,"value":16},
{"source":1,"target":3,"value":16},
{"source":1,"target":4,"value":4},
{"source":1,"target":3,"value":16},
{"source":1,"target":2,"value":16},
{"source":1,"target":4,"value":4},
{"source":1,"target":3,"value":16},
{"source":1,"target":2,"value":16},
{"source":2,"target":3,"value":25},
{"source":2,"target":3,"value":25},
{"source":2,"target":4,"value":9},
{"source":2,"target":5,"value":1},
{"source":2,"target":3,"value":25},
{"source":2,"target":4,"value":9},
{"source":2,"target":3,"value":25},
{"source":2,"target":3,"value":25},
{"source":2,"target":4,"value":9},
{"source":2,"target":3,"value":25},
{"source":3,"target":4,"value":9},
{"source":3,"target":5,"value":1},
{"source":3,"target":4,"value":9},
{"source":3,"target":4,"value":9},
{"source":4,"target":5,"value":1}
]
}