{
"nodes":[
{"name":"FAUST","group":5,"group1":1, "weight":100},
{"name":"MEPHISTOPHELES","group":5,"group1":1, "weight":100},
{"name":"WAGNER","group":5,"group1":3, "weight":100},
{"name":"KAYLINGER","group":5,"group1":3, "weight":100},
{"name":"MOOR","group":5,"group1":3, "weight":100},
{"name":"RÖSCHEN","group":5,"group1":4, "weight":100},
{"name":"FRANZ","group":5,"group1":7, "weight":100},
{"name":"CHOR","group":5,"group1":7, "weight":100},
{"name":"KUNIGUNDE","group":5,"group1":8, "weight":100},
{"name":"GULF","group":5,"group1":9, "weight":100},
{"name":"HUGO","group":5,"group1":10, "weight":100},
{"name":"KNAPPE","group":5,"group1":11, "weight":100},
{"name":"KUNIGUNDENS DIENERIN","group":5,"group1":17, "weight":100},
{"name":"BEGLEITER VON HUGO","group":5,"group1":18, "weight":100},
{"name":"GEISTER","group":5,"group1":20, "weight":100},
{"name":"EINE HEXE","group":5,"group1":1, "weight":100},
{"name":"SYCORAX","group":5,"group1":22, "weight":100},
{"name":"HEXEN","group":5,"group1":23, "weight":100},
{"name":"HOCHZEITSGÄSTE","group":5,"group1":31, "weight":100},
{"name":"CHOR DER MÄNNER","group":5,"group1":33, "weight":100},
{"name":"WOHLHALDT","group":5,"group1":3, "weight":100}
],
"links":[
{"source":0,"target":1,"value":169},
{"source":0,"target":5,"value":25},
{"source":0,"target":5,"value":25},
{"source":0,"target":1,"value":169},
{"source":0,"target":5,"value":25},
{"source":0,"target":1,"value":169},
{"source":0,"target":6,"value":16},
{"source":0,"target":7,"value":64},
{"source":0,"target":10,"value":100},
{"source":0,"target":10,"value":100},
{"source":0,"target":9,"value":16},
{"source":0,"target":10,"value":100},
{"source":0,"target":8,"value":81},
{"source":0,"target":10,"value":100},
{"source":0,"target":1,"value":169},
{"source":0,"target":9,"value":16},
{"source":0,"target":12,"value":1},
{"source":0,"target":1,"value":169},
{"source":0,"target":10,"value":100},
{"source":0,"target":10,"value":100},
{"source":0,"target":13,"value":1},
{"source":0,"target":7,"value":64},
{"source":0,"target":8,"value":81},
{"source":0,"target":10,"value":100},
{"source":0,"target":9,"value":16},
{"source":0,"target":1,"value":169},
{"source":0,"target":14,"value":1},
{"source":0,"target":9,"value":16},
{"source":0,"target":7,"value":64},
{"source":0,"target":8,"value":81},
{"source":0,"target":10,"value":100},
{"source":0,"target":1,"value":169},
{"source":0,"target":7,"value":64},
{"source":0,"target":1,"value":169},
{"source":0,"target":16,"value":4},
{"source":0,"target":16,"value":4},
{"source":0,"target":17,"value":1},
{"source":0,"target":1,"value":169},
{"source":0,"target":7,"value":64},
{"source":0,"target":6,"value":16},
{"source":0,"target":10,"value":100},
{"source":0,"target":8,"value":81},
{"source":0,"target":2,"value":16},
{"source":0,"target":20,"value":16},
{"source":0,"target":5,"value":25},
{"source":0,"target":10,"value":100},
{"source":0,"target":7,"value":64},
{"source":0,"target":5,"value":25},
{"source":0,"target":8,"value":81},
{"source":0,"target":1,"value":169},
{"source":0,"target":10,"value":100},
{"source":0,"target":6,"value":16},
{"source":0,"target":7,"value":64},
{"source":0,"target":19,"value":1},
{"source":0,"target":2,"value":16},
{"source":0,"target":8,"value":81},
{"source":0,"target":5,"value":25},
{"source":0,"target":6,"value":16},
{"source":0,"target":2,"value":16},
{"source":0,"target":1,"value":169},
{"source":0,"target":6,"value":16},
{"source":0,"target":2,"value":16},
{"source":0,"target":20,"value":16},
{"source":0,"target":8,"value":81},
{"source":0,"target":3,"value":4},
{"source":0,"target":8,"value":81},
{"source":0,"target":20,"value":16},
{"source":0,"target":2,"value":16},
{"source":0,"target":20,"value":16},
{"source":0,"target":3,"value":4},
{"source":0,"target":8,"value":81},
{"source":0,"target":20,"value":16},
{"source":0,"target":3,"value":4},
{"source":0,"target":1,"value":169},
{"source":0,"target":1,"value":169},
{"source":1,"target":5,"value":16},
{"source":1,"target":8,"value":49},
{"source":1,"target":10,"value":25},
{"source":1,"target":9,"value":9},
{"source":1,"target":12,"value":1},
{"source":1,"target":10,"value":25},
{"source":1,"target":10,"value":25},
{"source":1,"target":13,"value":1},
{"source":1,"target":7,"value":49},
{"source":1,"target":8,"value":49},
{"source":1,"target":10,"value":25},
{"source":1,"target":9,"value":9},
{"source":1,"target":14,"value":1},
{"source":1,"target":9,"value":9},
{"source":1,"target":7,"value":49},
{"source":1,"target":8,"value":49},
{"source":1,"target":10,"value":25},
{"source":1,"target":7,"value":49},
{"source":1,"target":16,"value":9},
{"source":1,"target":16,"value":9},
{"source":1,"target":17,"value":1},
{"source":1,"target":7,"value":49},
{"source":1,"target":5,"value":16},
{"source":1,"target":8,"value":49},
{"source":1,"target":10,"value":25},
{"source":1,"target":6,"value":9},
{"source":1,"target":7,"value":49},
{"source":1,"target":19,"value":1},
{"source":1,"target":7,"value":49},
{"source":1,"target":16,"value":9},
{"source":1,"target":5,"value":16},
{"source":1,"target":8,"value":49},
{"source":1,"target":20,"value":4},
{"source":1,"target":6,"value":9},
{"source":1,"target":8,"value":49},
{"source":1,"target":5,"value":16},
{"source":1,"target":6,"value":9},
{"source":1,"target":2,"value":4},
{"source":1,"target":6,"value":9},
{"source":1,"target":2,"value":4},
{"source":1,"target":2,"value":4},
{"source":1,"target":20,"value":4},
{"source":1,"target":3,"value":1},
{"source":1,"target":8,"value":49},
{"source":1,"target":20,"value":4},
{"source":1,"target":3,"value":1},
{"source":2,"target":20,"value":16},
{"source":2,"target":20,"value":16},
{"source":2,"target":3,"value":9},
{"source":2,"target":4,"value":4},
{"source":2,"target":3,"value":9},
{"source":2,"target":4,"value":4},
{"source":2,"target":20,"value":16},
{"source":2,"target":3,"value":9},
{"source":2,"target":4,"value":4},
{"source":2,"target":6,"value":9},
{"source":2,"target":5,"value":9},
{"source":2,"target":6,"value":9},
{"source":2,"target":10,"value":1},
{"source":2,"target":8,"value":9},
{"source":2,"target":20,"value":16},
{"source":2,"target":5,"value":9},
{"source":2,"target":8,"value":9},
{"source":2,"target":5,"value":9},
{"source":2,"target":6,"value":9},
{"source":2,"target":6,"value":9},
{"source":2,"target":20,"value":16},
{"source":2,"target":3,"value":9},
{"source":2,"target":8,"value":9},
{"source":2,"target":20,"value":16},
{"source":2,"target":3,"value":9},
{"source":3,"target":20,"value":16},
{"source":3,"target":20,"value":16},
{"source":3,"target":4,"value":4},
{"source":3,"target":4,"value":4},
{"source":3,"target":20,"value":16},
{"source":3,"target":4,"value":4},
{"source":3,"target":6,"value":1},
{"source":3,"target":5,"value":1},
{"source":3,"target":8,"value":4},
{"source":3,"target":20,"value":16},
{"source":3,"target":20,"value":16},
{"source":3,"target":8,"value":4},
{"source":3,"target":20,"value":16},
{"source":4,"target":20,"value":4},
{"source":4,"target":20,"value":4},
{"source":4,"target":20,"value":4},
{"source":4,"target":6,"value":1},
{"source":4,"target":5,"value":1},
{"source":5,"target":6,"value":64},
{"source":5,"target":6,"value":64},
{"source":5,"target":6,"value":64},
{"source":5,"target":20,"value":9},
{"source":5,"target":6,"value":64},
{"source":5,"target":6,"value":64},
{"source":5,"target":10,"value":4},
{"source":5,"target":8,"value":16},
{"source":5,"target":20,"value":9},
{"source":5,"target":8,"value":16},
{"source":5,"target":10,"value":4},
{"source":5,"target":6,"value":64},
{"source":5,"target":7,"value":1},
{"source":5,"target":19,"value":1},
{"source":5,"target":8,"value":16},
{"source":5,"target":20,"value":9},
{"source":5,"target":6,"value":64},
{"source":5,"target":8,"value":16},
{"source":5,"target":6,"value":64},
{"source":5,"target":6,"value":64},
{"source":6,"target":7,"value":4},
{"source":6,"target":20,"value":9},
{"source":6,"target":10,"value":4},
{"source":6,"target":8,"value":16},
{"source":6,"target":20,"value":9},
{"source":6,"target":8,"value":16},
{"source":6,"target":10,"value":4},
{"source":6,"target":7,"value":4},
{"source":6,"target":19,"value":1},
{"source":6,"target":8,"value":16},
{"source":6,"target":20,"value":9},
{"source":6,"target":8,"value":16},
{"source":7,"target":10,"value":36},
{"source":7,"target":10,"value":36},
{"source":7,"target":10,"value":36},
{"source":7,"target":13,"value":1},
{"source":7,"target":14,"value":1},
{"source":7,"target":9,"value":1},
{"source":7,"target":8,"value":9},
{"source":7,"target":10,"value":36},
{"source":7,"target":15,"value":1},
{"source":7,"target":16,"value":9},
{"source":7,"target":16,"value":9},
{"source":7,"target":17,"value":1},
{"source":7,"target":18,"value":1},
{"source":7,"target":10,"value":36},
{"source":7,"target":8,"value":9},
{"source":7,"target":10,"value":36},
{"source":7,"target":8,"value":9},
{"source":7,"target":10,"value":36},
{"source":7,"target":8,"value":9},
{"source":7,"target":10,"value":36},
{"source":7,"target":8,"value":9},
{"source":7,"target":10,"value":36},
{"source":7,"target":19,"value":1},
{"source":7,"target":16,"value":9},
{"source":8,"target":9,"value":16},
{"source":8,"target":10,"value":36},
{"source":8,"target":9,"value":16},
{"source":8,"target":12,"value":1},
{"source":8,"target":10,"value":36},
{"source":8,"target":9,"value":16},
{"source":8,"target":14,"value":1},
{"source":8,"target":9,"value":16},
{"source":8,"target":10,"value":36},
{"source":8,"target":10,"value":36},
{"source":8,"target":20,"value":25},
{"source":8,"target":18,"value":1},
{"source":8,"target":10,"value":36},
{"source":8,"target":10,"value":36},
{"source":8,"target":10,"value":36},
{"source":8,"target":10,"value":36},
{"source":8,"target":19,"value":1},
{"source":8,"target":20,"value":25},
{"source":8,"target":20,"value":25},
{"source":8,"target":20,"value":25},
{"source":8,"target":20,"value":25},
{"source":8,"target":20,"value":25},
{"source":9,"target":10,"value":16},
{"source":9,"target":10,"value":16},
{"source":9,"target":12,"value":1},
{"source":9,"target":10,"value":16},
{"source":9,"target":14,"value":1},
{"source":9,"target":10,"value":16},
{"source":10,"target":11,"value":1},
{"source":10,"target":12,"value":1},
{"source":10,"target":13,"value":1},
{"source":10,"target":14,"value":1},
{"source":10,"target":20,"value":1},
{"source":10,"target":18,"value":1},
{"source":10,"target":19,"value":1},
{"source":16,"target":17,"value":1}
]
}